[{"resourceType": "Encounter", "id": "40c5cfe4-8307-47de-a809-751c3ab1768d", "class": "ambulatory", "type": ["Encounter for problem"], "period": {"start": "1990-12-11T00:56:38+00:00", "end": "1990-12-11T01:11:38+00:00"}, "patient_id": "39a36ecd-f3a1-4b2b-a596-1f6de0111a5a"}, {"resourceType": "Encounter", "id": "5a7cb6ed-d402-4db2-a436-c9f9d1ce7bf4", "class": "ambulatory", "type": ["Encounter for problem"], "period": {"start": "1990-12-24T00:56:38+00:00", "end": "1990-12-24T01:45:38+00:00"}, "patient_id": "39a36ecd-f3a1-4b2b-a596-1f6de0111a5a"}, {"resourceType": "MedicationRequest", "id": "caa1f898-718f-456d-9c49-3d224d6e250a", "medicationCodeableConcept": "Terfenadine 60 MG Oral Tablet", "authoredOn": "1990-12-24T00:56:38+00:00", "dosageInstruction": [{"sequence": 1, "asNeededBoolean": true}], "patient_id": "39a36ecd-f3a1-4b2b-a596-1f6de0111a5a", "encounter_id": "5a7cb6ed-d402-4db2-a436-c9f9d1ce7bf4"}, {"resourceType": "MedicationRequest", "id": "fd4f2bc6-fac7-4f1e-b2eb-cbd02a62c682", "medicationCodeableConcept": "0.3 ML EPINEPHrine 0.5 MG/ML Auto-Injector", "authoredOn": "1990-12-24T00:56:38+00:00", "dosageInstruction": [{"sequence": 1, "asNeededBoolean": true}], "patient_id": "39a36ecd-f3a1-4b2b-a596-1f6de0111a5a", "encounter_id": "5a7cb6ed-d402-4db2-a436-c9f9d1ce7bf4"}, {"resourceType": "Encounter", "id": "c8056b60-dbd6-44fe-807c-1c1a7e565dd8", "class": "ambulatory", "type": ["Encounter for symptom"], "period": {"start": "1994-04-21T00:56:38+00:00", "end": "1994-04-21T01:26:38+00:00"}, "reason": [{"coding": [{"system": "http://snomed.info/sct", "code": "233678006", "display": "Childhood asthma"}]}], "patient_id": "39a36ecd-f3a1-4b2b-a596-1f6de0111a5a"}, {"resourceType": "MedicationRequest", "id": "c4b18168-0434-418a-88c6-96b721cae94d", "medicationCodeableConcept": "120 ACTUAT Fluticasone propionate 0.044 MG/ACTUAT Metered Dose Inhaler", "authoredOn": "1994-04-21T00:56:38+00:00", "dosageInstruction": [{"sequence": 1, "asNeededBoolean": true}], "patient_id": "39a36ecd-f3a1-4b2b-a596-1f6de0111a5a", "encounter_id": "c8056b60-dbd6-44fe-807c-1c1a7e565dd8"}, {"resourceType": "MedicationRequest", "id": "fe32df9c-270e-4f50-9d6d-2ea77067e0cc", "medicationCodeableConcept": "200 ACTUAT Albuterol 0.09 MG/ACTUAT Metered Dose Inhaler", "authoredOn": "1994-04-21T00:56:38+00:00", "dosageInstruction": [{"sequence": 1, "asNeededBoolean": true}], "patient_id": "39a36ecd-f3a1-4b2b-a596-1f6de0111a5a", "encounter_id": "c8056b60-dbd6-44fe-807c-1c1a7e565dd8"}, {"resourceType": "Encounter", "id": "0184ce93-d78f-4ea6-bbaa-d0c1def7efb9", "class": "ambulatory", "type": ["Encounter for symptom"], "period": {"start": "2011-11-09T00:56:38+00:00", "end": "2011-11-09T01:11:38+00:00"}, "reason": [{"coding": [{"system": "http://snomed.info/sct", "code": "444814009", "display": "Viral sinusitis (disorder)"}]}], "patient_id": "39a36ecd-f3a1-4b2b-a596-1f6de0111a5a"}, {"resourceType": "Condition", "id": "1ba4a301-9817-42a1-b4b2-7cb7eb204e44", "clinicalStatus": "resolved", "code": "Viral sinusitis (disorder)", "onsetDateTime": "2011-11-09T00:56:38+00:00", "patient_id": "39a36ecd-f3a1-4b2b-a596-1f6de0111a5a", "encounter_id": "0184ce93-d78f-4ea6-bbaa-d0c1def7efb9"}, {"resourceType": "Encounter", "id": "f8a25ecb-1f99-44e9-af1b-192ae03d7588", "class": "ambulatory", "type": ["Encounter for symptom"], "period": {"start": "2012-05-07T00:56:38+00:00", "end": "2012-05-07T01:11:38+00:00"}, "reason": [{"coding": [{"system": "http://snomed.info/sct", "code": "444814009", "display": "Viral sinusitis (disorder)"}]}], "patient_id": "39a36ecd-f3a1-4b2b-a596-1f6de0111a5a"}, {"resourceType": "Condition", "id": "5478da8d-1c2e-4403-9150-944512b40131", "clinicalStatus": "resolved", "code": "Viral sinusitis (disorder)", "onsetDateTime": "2012-05-07T00:56:38+00:00", "patient_id": "39a36ecd-f3a1-4b2b-a596-1f6de0111a5a", "encounter_id": "f8a25ecb-1f99-44e9-af1b-192ae03d7588"}, {"resourceType": "Encounter", "id": "e95d9e3c-135f-4fe0-a03a-b5a7ad2a59ed", "class": "WELLNESS", "type": ["Encounter for check up (procedure)"], "period": {"start": "2012-05-27T00:56:38+00:00", "end": "2012-05-27T01:26:38+00:00"}, "patient_id": "39a36ecd-f3a1-4b2b-a596-1f6de0111a5a"}, {"resourceType": "Observation", "id": "ef336dcb-23e8-4247-b06b-420c8d8865cc", "code": "Body Height", "effectiveDateTime": "2012-05-27T00:56:38+00:00", "patient_id": "39a36ecd-f3a1-4b2b-a596-1f6de0111a5a", "encounter_id": "e95d9e3c-135f-4fe0-a03a-b5a7ad2a59ed", "value": 189.6515226924659, "unit": "cm"}, {"resourceType": "Observation", "id": "56adfa3f-9656-4bbc-9f9a-7d8c3c195107", "code": "Body Weight", "effectiveDateTime": "2012-05-27T00:56:38+00:00", "patient_id": "39a36ecd-f3a1-4b2b-a596-1f6de0111a5a", "encounter_id": "e95d9e3c-135f-4fe0-a03a-b5a7ad2a59ed", "value": 84.2427104079603, "unit": "kg"}, {"resourceType": "Observation", "id": "f80c802d-0d20-4583-b256-b5724553a49a", "code": "Body Mass Index", "effectiveDateTime": "2012-05-27T00:56:38+00:00", "patient_id": "39a36ecd-f3a1-4b2b-a596-1f6de0111a5a", "encounter_id": "e95d9e3c-135f-4fe0-a03a-b5a7ad2a59ed", "value": 23.42176738252229, "unit": "kg/m2"}, {"resourceType": "Observation", "id": "4faec230-af80-4eb5-baf9-d396c0c2693e", "code": "Blood Pressure", "effectiveDateTime": "2012-05-27T00:56:38+00:00", "component": [{"code": "Diastolic Blood Pressure", "value": 78.96004713624146, "unit": "mmHg"}, {"code": "Systolic Blood Pressure", "value": 119.46479088676651, "unit": "mmHg"}], "patient_id": "39a36ecd-f3a1-4b2b-a596-1f6de0111a5a", "encounter_id": "e95d9e3c-135f-4fe0-a03a-b5a7ad2a59ed"}, {"resourceType": "Procedure", "id": "7e6777c9-eb0b-4065-9e18-87e42d5adf31", "code": "Documentation of current medications", "performedPeriod": {"start": "2012-05-27T00:56:38+00:00", "end": "2012-05-27T01:11:38+00:00"}, "patient_id": "39a36ecd-f3a1-4b2b-a596-1f6de0111a5a", "encounter_id": "e95d9e3c-135f-4fe0-a03a-b5a7ad2a59ed"}, {"resourceType": "Encounter", "id": "4c1f144e-08be-49ea-8617-4fff93104ab5", "class": "ambulatory", "type": ["Encounter for symptom"], "period": {"start": "2012-06-14T00:56:38+00:00", "end": "2012-06-14T01:11:38+00:00"}, "reason": [{"coding": [{"system": "http://snomed.info/sct", "code": "195662009", "display": "Acute viral pharyngitis (disorder)"}]}], "patient_id": "39a36ecd-f3a1-4b2b-a596-1f6de0111a5a"}, {"resourceType": "Condition", "id": "4a79de6a-9150-4e51-a8d3-33dec701ba41", "clinicalStatus": "resolved", "code": "Acute viral pharyngitis (disorder)", "onsetDateTime": "2012-06-14T00:56:38+00:00", "patient_id": "39a36ecd-f3a1-4b2b-a596-1f6de0111a5a", "encounter_id": "4c1f144e-08be-49ea-8617-4fff93104ab5"}, {"resourceType": "Observation", "id": "a681ac00-032f-4ce0-bb76-263c96066cec", "code": "Oral temperature", "effectiveDateTime": "2012-06-14T00:56:38+00:00", "patient_id": "39a36ecd-f3a1-4b2b-a596-1f6de0111a5a", "encounter_id": "4c1f144e-08be-49ea-8617-4fff93104ab5", "value": 37.91651385986332, "unit": "Cel"}, {"resourceType": "Encounter", "id": "f571dcc1-aff4-4934-9b9e-9b5d196cc244", "class": "ambulatory", "type": ["Asthma follow-up"], "period": {"start": "2012-11-23T00:56:38+00:00", "end": "2012-11-23T01:11:38+00:00"}, "reason": [{"coding": [{"system": "http://snomed.info/sct", "code": "195967001", "display": "Asthma"}]}], "patient_id": "39a36ecd-f3a1-4b2b-a596-1f6de0111a5a"}, {"resourceType": "Condition", "id": "3c677660-37a3-4712-8286-4f3a0ccaa852", "clinicalStatus": "active", "code": "Asthma", "onsetDateTime": "2012-11-23T00:56:38+00:00", "patient_id": "39a36ecd-f3a1-4b2b-a596-1f6de0111a5a", "encounter_id": "f571dcc1-aff4-4934-9b9e-9b5d196cc244"}, {"resourceType": "Encounter", "id": "90e8a537-496d-4871-89be-1027da90a3d8", "class": "ambulatory", "type": ["Asthma follow-up"], "period": {"start": "2013-05-22T00:56:38+00:00", "end": "2013-05-22T01:11:38+00:00"}, "reason": [{"coding": [{"system": "http://snomed.info/sct", "code": "195967001", "display": "Asthma"}]}], "patient_id": "39a36ecd-f3a1-4b2b-a596-1f6de0111a5a"}, {"resourceType": "Encounter", "id": "6c4254e2-d0b8-4c0f-aea5-88a0259107c6", "class": "ambulatory", "type": ["Asthma follow-up"], "period": {"start": "2014-05-17T00:56:38+00:00", "end": "2014-05-17T01:11:38+00:00"}, "reason": [{"coding": [{"system": "http://snomed.info/sct", "code": "195967001", "display": "Asthma"}]}], "patient_id": "39a36ecd-f3a1-4b2b-a596-1f6de0111a5a"}, {"resourceType": "Encounter", "id": "2e51881c-072d-4369-ac52-cd5e47d64faf", "class": "WELLNESS", "type": ["Encounter for check up (procedure)"], "period": {"start": "2015-05-31T00:56:38+00:00", "end": "2015-05-31T01:11:38+00:00"}, "patient_id": "39a36ecd-f3a1-4b2b-a596-1f6de0111a5a"}, {"resourceType": "Condition", "id": "c84e1b4e-3e77-4dc4-aef3-2d14f4a7ec0b", "clinicalStatus": "active", "code": "Prediabetes", "onsetDateTime": "2015-05-31T00:56:38+00:00", "patient_id": "39a36ecd-f3a1-4b2b-a596-1f6de0111a5a", "encounter_id": "2e51881c-072d-4369-ac52-cd5e47d64faf"}, {"resourceType": "Observation", "id": "d2ffd913-9599-4fc4-873e-0b3fd4627973", "code": "Body Height", "effectiveDateTime": "2015-05-31T00:56:38+00:00", "patient_id": "39a36ecd-f3a1-4b2b-a596-1f6de0111a5a", "encounter_id": "2e51881c-072d-4369-ac52-cd5e47d64faf", "value": 189.6515226924659, "unit": "cm"}, {"resourceType": "Observation", "id": "b959756d-50cd-4b3c-9afd-ece3c44643e6", "code": "Body Weight", "effectiveDateTime": "2015-05-31T00:56:38+00:00", "patient_id": "39a36ecd-f3a1-4b2b-a596-1f6de0111a5a", "encounter_id": "2e51881c-072d-4369-ac52-cd5e47d64faf", "value": 88.23758680668445, "unit": "kg"}, {"resourceType": "Observation", "id": "9fd35d7a-6c2a-4553-84b5-eae07a61f973", "code": "Body Mass Index", "effectiveDateTime": "2015-05-31T00:56:38+00:00", "patient_id": "39a36ecd-f3a1-4b2b-a596-1f6de0111a5a", "encounter_id": "2e51881c-072d-4369-ac52-cd5e47d64faf", "value": 24.532451799960075, "unit": "kg/m2"}, {"resourceType": "Observation", "id": "178155e5-667d-476b-b674-91b91faa6135", "code": "Blood Pressure", "effectiveDateTime": "2015-05-31T00:56:38+00:00", "component": [{"code": "Diastolic Blood Pressure", "value": 87.30843010940713, "unit": "mmHg"}, {"code": "Systolic Blood Pressure", "value": 120.53496374702063, "unit": "mmHg"}], "patient_id": "39a36ecd-f3a1-4b2b-a596-1f6de0111a5a", "encounter_id": "2e51881c-072d-4369-ac52-cd5e47d64faf"}, {"resourceType": "Observation", "id": "37e89800-d1dd-427d-a770-3d45cd850ec6", "code": "Hemoglobin A1c/Hemoglobin.total in Blood", "effectiveDateTime": "2015-05-31T00:56:38+00:00", "patient_id": "39a36ecd-f3a1-4b2b-a596-1f6de0111a5a", "encounter_id": "2e51881c-072d-4369-ac52-cd5e47d64faf", "value": 6.238577213080083, "unit": "%"}, {"resourceType": "Encounter", "id": "b4c882b8-7c2d-4be7-a81e-228c5746b360", "class": "ambulatory", "type": ["Encounter for symptom"], "period": {"start": "2016-04-10T00:56:38+00:00", "end": "2016-04-10T01:26:38+00:00"}, "reason": [{"coding": [{"system": "http://snomed.info/sct", "code": "195662009", "display": "Acute viral pharyngitis (disorder)"}]}], "patient_id": "39a36ecd-f3a1-4b2b-a596-1f6de0111a5a"}, {"resourceType": "Condition", "id": "ccb4a688-13d6-44a5-9cc8-d6fe5c320e4b", "clinicalStatus": "resolved", "code": "Acute viral pharyngitis (disorder)", "onsetDateTime": "2016-04-10T00:56:38+00:00", "patient_id": "39a36ecd-f3a1-4b2b-a596-1f6de0111a5a", "encounter_id": "b4c882b8-7c2d-4be7-a81e-228c5746b360"}, {"resourceType": "Observation", "id": "4cc2a134-38d7-4aa1-88c0-1d0a14a1ca9f", "code": "Oral temperature", "effectiveDateTime": "2016-04-10T00:56:38+00:00", "patient_id": "39a36ecd-f3a1-4b2b-a596-1f6de0111a5a", "encounter_id": "b4c882b8-7c2d-4be7-a81e-228c5746b360", "value": 37.60809421532809, "unit": "Cel"}, {"resourceType": "Procedure", "id": "1c1536b2-f5e7-4877-b1e0-a4be74eabb05", "code": "Throat culture (procedure) ", "performedPeriod": {"start": "2016-04-10T00:56:38+00:00", "end": "2016-04-10T01:11:38+00:00"}, "reasonReference": [{"reference": "urn:uuid:4a79de6a-9150-4e51-a8d3-33dec701ba41", "display": "Acute viral pharyngitis (disorder)"}, {"reference": "urn:uuid:ccb4a688-13d6-44a5-9cc8-d6fe5c320e4b", "display": "Acute viral pharyngitis (disorder)"}], "patient_id": "39a36ecd-f3a1-4b2b-a596-1f6de0111a5a", "encounter_id": "b4c882b8-7c2d-4be7-a81e-228c5746b360"}, {"resourceType": "Encounter", "id": "15c008ae-a98f-4388-9bc1-f2791f8b7456", "class": "WELLNESS", "type": ["Encounter for check up (procedure)"], "period": {"start": "2016-04-17T00:56:38+00:00", "end": "2016-04-17T01:26:38+00:00"}, "patient_id": "39a36ecd-f3a1-4b2b-a596-1f6de0111a5a"}, {"resourceType": "Observation", "id": "4393965b-e3e1-400c-bbe4-dbcd1262a546", "code": "Body Height", "effectiveDateTime": "2016-04-17T00:56:38+00:00", "patient_id": "39a36ecd-f3a1-4b2b-a596-1f6de0111a5a", "encounter_id": "15c008ae-a98f-4388-9bc1-f2791f8b7456", "value": 189.6515226924659, "unit": "cm"}, {"resourceType": "Observation", "id": "90f4e984-51cc-45cb-afbe-d4a27e6fffaa", "code": "Body Weight", "effectiveDateTime": "2016-04-17T00:56:38+00:00", "patient_id": "39a36ecd-f3a1-4b2b-a596-1f6de0111a5a", "encounter_id": "15c008ae-a98f-4388-9bc1-f2791f8b7456", "value": 88.23758680668445, "unit": "kg"}, {"resourceType": "Observation", "id": "cf003327-6697-4147-8970-e7bbdf8ac1f3", "code": "Body Mass Index", "effectiveDateTime": "2016-04-17T00:56:38+00:00", "patient_id": "39a36ecd-f3a1-4b2b-a596-1f6de0111a5a", "encounter_id": "15c008ae-a98f-4388-9bc1-f2791f8b7456", "value": 24.532451799960075, "unit": "kg/m2"}, {"resourceType": "Observation", "id": "574ba93e-11e4-4667-9157-55af84dfb673", "code": "Blood Pressure", "effectiveDateTime": "2016-04-17T00:56:38+00:00", "component": [{"code": "Diastolic Blood Pressure", "value": 82.3407914145796, "unit": "mmHg"}, {"code": "Systolic Blood Pressure", "value": 101.83423245820505, "unit": "mmHg"}], "patient_id": "39a36ecd-f3a1-4b2b-a596-1f6de0111a5a", "encounter_id": "15c008ae-a98f-4388-9bc1-f2791f8b7456"}, {"resourceType": "Observation", "id": "368445d9-8f59-4121-8f01-d572419d40a7", "code": "Hemoglobin A1c/Hemoglobin.total in Blood", "effectiveDateTime": "2016-04-17T00:56:38+00:00", "patient_id": "39a36ecd-f3a1-4b2b-a596-1f6de0111a5a", "encounter_id": "15c008ae-a98f-4388-9bc1-f2791f8b7456", "value": 6.335435476072546, "unit": "%"}, {"resourceType": "Observation", "id": "46ade378-7fa8-4715-8f0c-bf3172b97e41", "code": "Glucose", "effectiveDateTime": "2016-04-17T00:56:38+00:00", "patient_id": "39a36ecd-f3a1-4b2b-a596-1f6de0111a5a", "encounter_id": "15c008ae-a98f-4388-9bc1-f2791f8b7456", "value": 77.01105041412725, "unit": "mg/dL"}, {"resourceType": "Observation", "id": "72d06629-8afc-45a5-b7df-797b833044be", "code": "Urea Nitrogen", "effectiveDateTime": "2016-04-17T00:56:38+00:00", "patient_id": "39a36ecd-f3a1-4b2b-a596-1f6de0111a5a", "encounter_id": "15c008ae-a98f-4388-9bc1-f2791f8b7456", "value": 8.23645323354514, "unit": "mg/dL"}, {"resourceType": "Observation", "id": "897c000a-31e0-49c9-90ac-08886b7359a7", "code": "Creatinine", "effectiveDateTime": "2016-04-17T00:56:38+00:00", "patient_id": "39a36ecd-f3a1-4b2b-a596-1f6de0111a5a", "encounter_id": "15c008ae-a98f-4388-9bc1-f2791f8b7456", "value": 1.4093503448289877, "unit": "mg/dL"}, {"resourceType": "Observation", "id": "2888daa6-c35b-4ea7-991b-ab47efc77ca3", "code": "Calcium", "effectiveDateTime": "2016-04-17T00:56:38+00:00", "patient_id": "39a36ecd-f3a1-4b2b-a596-1f6de0111a5a", "encounter_id": "15c008ae-a98f-4388-9bc1-f2791f8b7456", "value": 8.911609651638372, "unit": "mg/dL"}, {"resourceType": "Observation", "id": "2e3113d6-2018-4e69-9134-74afd9a0ebe8", "code": "Sodium", "effectiveDateTime": "2016-04-17T00:56:38+00:00", "patient_id": "39a36ecd-f3a1-4b2b-a596-1f6de0111a5a", "encounter_id": "15c008ae-a98f-4388-9bc1-f2791f8b7456", "value": 139.3252387707859, "unit": "mmol/L"}, {"resourceType": "Observation", "id": "a07e9a70-f783-494c-8727-cb6ad21d5e86", "code": "Potassium", "effectiveDateTime": "2016-04-17T00:56:38+00:00", "patient_id": "39a36ecd-f3a1-4b2b-a596-1f6de0111a5a", "encounter_id": "15c008ae-a98f-4388-9bc1-f2791f8b7456", "value": 4.408835749614286, "unit": "mmol/L"}, {"resourceType": "Observation", "id": "d7e30837-5bd7-4be9-91f1-e6f410c68af0", "code": "Chloride", "effectiveDateTime": "2016-04-17T00:56:38+00:00", "patient_id": "39a36ecd-f3a1-4b2b-a596-1f6de0111a5a", "encounter_id": "15c008ae-a98f-4388-9bc1-f2791f8b7456", "value": 109.071551097059, "unit": "mmol/L"}, {"resourceType": "Observation", "id": "dfb35ea3-b5b5-47f0-9705-c06746e3b9b3", "code": "Carbon Dioxide", "effectiveDateTime": "2016-04-17T00:56:38+00:00", "patient_id": "39a36ecd-f3a1-4b2b-a596-1f6de0111a5a", "encounter_id": "15c008ae-a98f-4388-9bc1-f2791f8b7456", "value": 22.955851700735003, "unit": "mmol/L"}, {"resourceType": "Observation", "id": "85fd9da6-128d-4021-b0e4-d42d86581b18", "code": "Hemoglobin A1c/Hemoglobin.total in Blood", "effectiveDateTime": "2016-04-17T00:56:38+00:00", "patient_id": "39a36ecd-f3a1-4b2b-a596-1f6de0111a5a", "encounter_id": "15c008ae-a98f-4388-9bc1-f2791f8b7456", "value": 6.3307963248865855, "unit": "%"}, {"resourceType": "Procedure", "id": "5b2512fc-187a-4d4b-85a0-53fcbc6a2211", "code": "Documentation of current medications", "performedPeriod": {"start": "2016-04-17T00:56:38+00:00", "end": "2016-04-17T01:11:38+00:00"}, "patient_id": "39a36ecd-f3a1-4b2b-a596-1f6de0111a5a", "encounter_id": "15c008ae-a98f-4388-9bc1-f2791f8b7456"}, {"resourceType": "Encounter", "id": "8bfc060f-1e0d-481e-8c18-38fc618bca2f", "class": "ambulatory", "type": ["Asthma follow-up"], "period": {"start": "2016-05-06T00:56:38+00:00", "end": "2016-05-06T01:11:38+00:00"}, "reason": [{"coding": [{"system": "http://snomed.info/sct", "code": "195967001", "display": "Asthma"}]}], "patient_id": "39a36ecd-f3a1-4b2b-a596-1f6de0111a5a"}, {"resourceType": "Encounter", "id": "295d1599-1246-41dd-b87c-30829799ae2c", "class": "ambulatory", "type": ["Asthma follow-up"], "period": {"start": "2016-11-02T00:56:38+00:00", "end": "2016-11-02T01:11:38+00:00"}, "reason": [{"coding": [{"system": "http://snomed.info/sct", "code": "195967001", "display": "Asthma"}]}], "patient_id": "39a36ecd-f3a1-4b2b-a596-1f6de0111a5a"}, {"resourceType": "Encounter", "id": "bec8d194-fbcc-4ea4-b083-89ad8bb8696c", "class": "ambulatory", "type": ["Asthma follow-up"], "period": {"start": "2017-10-28T00:56:38+00:00", "end": "2017-10-28T01:11:38+00:00"}, "reason": [{"coding": [{"system": "http://snomed.info/sct", "code": "195967001", "display": "Asthma"}]}], "patient_id": "39a36ecd-f3a1-4b2b-a596-1f6de0111a5a"}, {"resourceType": "Encounter", "id": "a7e3804c-f798-4f15-9405-2a4e74f64715", "class": "WELLNESS", "type": ["Encounter for check up (procedure)"], "period": {"start": "2019-04-21T00:56:38+00:00", "end": "2019-04-21T01:11:38+00:00"}, "patient_id": "39a36ecd-f3a1-4b2b-a596-1f6de0111a5a"}, {"resourceType": "Condition", "id": "e2a417d8-189c-4911-838f-68cc828ded45", "clinicalStatus": "active", "code": "Diabetes", "onsetDateTime": "2019-04-21T00:56:38+00:00", "patient_id": "39a36ecd-f3a1-4b2b-a596-1f6de0111a5a", "encounter_id": "a7e3804c-f798-4f15-9405-2a4e74f64715"}, {"resourceType": "Condition", "id": "62adf556-7665-48f8-893e-4e59005b0953", "clinicalStatus": "active", "code": "Neuropathy due to type 2 diabetes mellitus (disorder)", "onsetDateTime": "2019-04-21T00:56:38+00:00", "patient_id": "39a36ecd-f3a1-4b2b-a596-1f6de0111a5a", "encounter_id": "a7e3804c-f798-4f15-9405-2a4e74f64715"}, {"resourceType": "Observation", "id": "eab38ba2-9e01-41cd-88f5-44bd1eecd9d8", "code": "Body Height", "effectiveDateTime": "2019-04-21T00:56:38+00:00", "patient_id": "39a36ecd-f3a1-4b2b-a596-1f6de0111a5a", "encounter_id": "a7e3804c-f798-4f15-9405-2a4e74f64715", "value": 189.6515226924659, "unit": "cm"}, {"resourceType": "Observation", "id": "a498f98c-9d9a-4493-8c99-7ddcff91c3b5", "code": "Body Weight", "effectiveDateTime": "2019-04-21T00:56:38+00:00", "patient_id": "39a36ecd-f3a1-4b2b-a596-1f6de0111a5a", "encounter_id": "a7e3804c-f798-4f15-9405-2a4e74f64715", "value": 93.71706894594148, "unit": "kg"}, {"resourceType": "Observation", "id": "098baafc-687b-41cd-b67d-7f1f06e3b6b8", "code": "Body Mass Index", "effectiveDateTime": "2019-04-21T00:56:38+00:00", "patient_id": "39a36ecd-f3a1-4b2b-a596-1f6de0111a5a", "encounter_id": "a7e3804c-f798-4f15-9405-2a4e74f64715", "value": 26.055897038377246, "unit": "kg/m2"}, {"resourceType": "Observation", "id": "fd85e6fa-2247-4259-a63c-ebb4f9441838", "code": "Blood Pressure", "effectiveDateTime": "2019-04-21T00:56:38+00:00", "component": [{"code": "Diastolic Blood Pressure", "value": 70.94984847223039, "unit": "mmHg"}, {"code": "Systolic Blood Pressure", "value": 105.79461416699888, "unit": "mmHg"}], "patient_id": "39a36ecd-f3a1-4b2b-a596-1f6de0111a5a", "encounter_id": "a7e3804c-f798-4f15-9405-2a4e74f64715"}, {"resourceType": "Observation", "id": "e1506bac-6fa3-4f86-b1d0-0cd3a1b05ee2", "code": "Hemoglobin A1c/Hemoglobin.total in Blood", "effectiveDateTime": "2019-04-21T00:56:38+00:00", "patient_id": "39a36ecd-f3a1-4b2b-a596-1f6de0111a5a", "encounter_id": "a7e3804c-f798-4f15-9405-2a4e74f64715", "value": 6.6, "unit": "%"}, {"resourceType": "Observation", "id": "5fa2e5f7-7ced-4fe5-8414-7a7654402f07", "code": "Glucose", "effectiveDateTime": "2019-04-21T00:56:38+00:00", "patient_id": "39a36ecd-f3a1-4b2b-a596-1f6de0111a5a", "encounter_id": "a7e3804c-f798-4f15-9405-2a4e74f64715", "value": 71.64867530160777, "unit": "mg/dL"}, {"resourceType": "Observation", "id": "00b218ad-afa8-4187-87e3-3fe0a2ba5381", "code": "Urea Nitrogen", "effectiveDateTime": "2019-04-21T00:56:38+00:00", "patient_id": "39a36ecd-f3a1-4b2b-a596-1f6de0111a5a", "encounter_id": "a7e3804c-f798-4f15-9405-2a4e74f64715", "value": 16.583850898368034, "unit": "mg/dL"}, {"resourceType": "Observation", "id": "9bf6b18c-9907-4f38-a70f-feacfe939c7b", "code": "Creatinine", "effectiveDateTime": "2019-04-21T00:56:38+00:00", "patient_id": "39a36ecd-f3a1-4b2b-a596-1f6de0111a5a", "encounter_id": "a7e3804c-f798-4f15-9405-2a4e74f64715", "value": 1.457821072492423, "unit": "mg/dL"}, {"resourceType": "Observation", "id": "e801305a-7b34-4fa9-9298-19b23cafffc7", "code": "Calcium", "effectiveDateTime": "2019-04-21T00:56:38+00:00", "patient_id": "39a36ecd-f3a1-4b2b-a596-1f6de0111a5a", "encounter_id": "a7e3804c-f798-4f15-9405-2a4e74f64715", "value": 10.05464840483223, "unit": "mg/dL"}, {"resourceType": "Observation", "id": "eb8f8f37-1140-4f8a-9ffb-f59900468bd3", "code": "Sodium", "effectiveDateTime": "2019-04-21T00:56:38+00:00", "patient_id": "39a36ecd-f3a1-4b2b-a596-1f6de0111a5a", "encounter_id": "a7e3804c-f798-4f15-9405-2a4e74f64715", "value": 136.90566551729836, "unit": "mmol/L"}, {"resourceType": "Observation", "id": "e29186fe-0923-41c4-b179-d1d9ebc48e67", "code": "Potassium", "effectiveDateTime": "2019-04-21T00:56:38+00:00", "patient_id": "39a36ecd-f3a1-4b2b-a596-1f6de0111a5a", "encounter_id": "a7e3804c-f798-4f15-9405-2a4e74f64715", "value": 4.6566632832283545, "unit": "mmol/L"}, {"resourceType": "Observation", "id": "2d196235-edb6-430a-99d8-d7017be1ea76", "code": "Chloride", "effectiveDateTime": "2019-04-21T00:56:38+00:00", "patient_id": "39a36ecd-f3a1-4b2b-a596-1f6de0111a5a", "encounter_id": "a7e3804c-f798-4f15-9405-2a4e74f64715", "value": 108.9479004798372, "unit": "mmol/L"}, {"resourceType": "Observation", "id": "d58b6b9b-8d3c-41ce-99c2-e86245ce182d", "code": "Carbon Dioxide", "effectiveDateTime": "2019-04-21T00:56:38+00:00", "patient_id": "39a36ecd-f3a1-4b2b-a596-1f6de0111a5a", "encounter_id": "a7e3804c-f798-4f15-9405-2a4e74f64715", "value": 20.567189625033063, "unit": "mmol/L"}, {"resourceType": "Observation", "id": "ae1ac1ea-82fe-4c07-ab49-dcc5f7d6faa3", "code": "Hemoglobin A1c/Hemoglobin.total in Blood", "effectiveDateTime": "2019-04-21T00:56:38+00:00", "patient_id": "39a36ecd-f3a1-4b2b-a596-1f6de0111a5a", "encounter_id": "a7e3804c-f798-4f15-9405-2a4e74f64715", "value": 6.6, "unit": "%"}]